SBILoops/__init__.py
SBILoops/beans/Executable.py
SBILoops/beans/File.py
SBILoops/beans/IndexedNum.py
SBILoops/beans/JSONer.py
SBILoops/beans/Path.py
SBILoops/beans/StorableObject.py
SBILoops/beans/__init__.py
SBILoops/beans/butler.py
SBILoops/beans/singleton.py
SBILoops/data/Alphabet.py
SBILoops/data/AminoAcids.py
SBILoops/data/AtomVariants.py
SBILoops/data/Element.py
SBILoops/data/Properties.py
SBILoops/data/SetDict.py
SBILoops/data/__init__.py
SBILoops/databases/CATHlink.py
SBILoops/databases/DrugBanklink.py
SBILoops/databases/Enzymelink.py
SBILoops/databases/GOlink.py
SBILoops/databases/PDBTMlink.py
SBILoops/databases/PDBeChemConnect.py
SBILoops/databases/PDBeChemlink.py
SBILoops/databases/PDBlink.py
SBILoops/databases/SCOPlink.py
SBILoops/databases/TaxIDlink.py
SBILoops/databases/Uniprotlink.py
SBILoops/databases/__Uniprotlink.py
SBILoops/databases/__init__.py
SBILoops/databases/dblink.py
SBILoops/databases/uniprot/__init__.py
SBILoops/databases/uniprot/connect.py
SBILoops/databases/uniprot/uniprot.py
SBILoops/error/BlastError.py
SBILoops/error/FileError.py
SBILoops/error/SeqAliError.py
SBILoops/error/__init__.py
SBILoops/external/README.md
SBILoops/external/__init__.py
SBILoops/external/configSBI.txt
SBILoops/external/CDhit/CDhit.py
SBILoops/external/CDhit/CDhitExe.py
SBILoops/external/CDhit/CDhitHomolog.py
SBILoops/external/CDhit/CDhitList.py
SBILoops/external/CDhit/__init__.py
SBILoops/external/DSSP/DSSP.py
SBILoops/external/DSSP/DSSPExe.py
SBILoops/external/DSSP/__init__.py
SBILoops/external/blast/BlastExe.py
SBILoops/external/blast/BlastHit.py
SBILoops/external/blast/BlastResult.py
SBILoops/external/blast/__init__.py
SBILoops/external/blast/blast_parser.py
SBILoops/math/__init__.py
SBILoops/math/stats.py
SBILoops/sequence/Fasta.py
SBILoops/sequence/IndexedSeqAli.py
SBILoops/sequence/SeqAli.py
SBILoops/sequence/Sequence.py
SBILoops/sequence/__init__.py
SBILoops/sequence/alignment/Needleman_Wunsch.py
SBILoops/sequence/alignment/SeqAli.py
SBILoops-0.3.0.dist-info/METADATA
SBILoops-0.3.0.dist-info/WHEEL
SBILoops-0.3.0.dist-info/top_level.txt
SBILoops-0.3.0.dist-info/RECORD
